nifcloud_cli-1.17.0.data/scripts/nifcloud
nifcloud_cli-1.17.0.dist-info/licenses/LICENSE
nifcloudcli/__init__.py
nifcloudcli/clidriver.py
nifcloudcli/constants.py
nifcloudcli/link.py
nifcloudcli/customizations/__init__.py
nifcloudcli/customizations/commands.py
nifcloudcli/customizations/waiters.py
nifcloudcli/customizations/configure/__init__.py
nifcloudcli/customizations/configure/addmodel.py
nifcloudcli/customizations/configure/configure.py
nifcloudcli/customizations/configure/get.py
nifcloudcli/customizations/configure/list.py
nifcloudcli/customizations/configure/set.py
nifcloudcli/data/_retry.json
nifcloudcli/data/cli.json
nifcloudcli/data/endpoints.json
nifcloudcli/data/sdk-default-configuration.json
nifcloudcli/data/computing/3.0/service-2.json
nifcloudcli/data/computing/3.0/waiters-2.json
nifcloudcli/data/devops/v1/service-2.json
nifcloudcli/data/devops-runner/v1/service-2.json
nifcloudcli/data/dns/2012-12-12N2013-12-16/service-2.json
nifcloudcli/data/ess/2010-12-01N2014-05-28/service-2.json
nifcloudcli/data/nas/N2016-02-24/service-2.json
nifcloudcli/data/nas/N2016-02-24/waiters-2.json
nifcloudcli/data/rdb/2013-05-15N2013-12-16/service-2.json
nifcloudcli/data/rdb/2013-05-15N2013-12-16/waiters-2.json
nifcloudcli/data/service-activity/2020-11-25/service-2.json
nifcloudcli/data/storage/2006-03-01/service-2.json
nifcloudcli/topics/topic-tags.json
nifcloud_cli-1.17.0.dist-info/METADATA
nifcloud_cli-1.17.0.dist-info/WHEEL
nifcloud_cli-1.17.0.dist-info/top_level.txt
nifcloud_cli-1.17.0.dist-info/RECORD
