Metadata-Version: 2.4
Name: nifcloud-cli
Version: 1.17.0
Summary: NIFCLOUD Command-Line Tools
Home-page: https://github.com/nifcloud/nifcloud-cli
Author: Fujitsu
License: Apache-2.0
Project-URL: Homepage, https://github.com/nifcloud/nifcloud-cli
Classifier: Development Status :: 5 - Production/Stable
Classifier: Intended Audience :: Developers
Classifier: Intended Audience :: System Administrators
Classifier: Natural Language :: English
Classifier: License :: OSI Approved :: Apache Software License
Classifier: Programming Language :: Python
Classifier: Programming Language :: Python :: 3.8
Classifier: Programming Language :: Python :: 3.9
Classifier: Programming Language :: Python :: 3.10
Classifier: Programming Language :: Python :: 3.11
Classifier: Programming Language :: Python :: 3.12
Classifier: Programming Language :: Python :: 3.13
Requires-Python: >=3.8
License-File: LICENSE
Requires-Dist: awscli==1.38.10
Requires-Dist: nifcloud==1.17.0
Requires-Dist: pyyaml==5.3.1
Dynamic: home-page
Dynamic: license-file
